neverland_compiler/__init__.py
neverland_compiler/compile.py
neverland_compiler-0.2.0.dist-info/LICENSE
neverland_compiler-0.2.0.dist-info/METADATA
neverland_compiler-0.2.0.dist-info/WHEEL
neverland_compiler-0.2.0.dist-info/entry_points.txt
neverland_compiler-0.2.0.dist-info/top_level.txt
neverland_compiler-0.2.0.dist-info/RECORD
