Metadata-Version: 2.1
Name: neverland-compiler
Version: 0.2.0
Author-email: umaru <529280602@qq.com>
License: MIT
Classifier: Programming Language :: Python :: 3
Classifier: License :: OSI Approved :: MIT License
Classifier: Operating System :: OS Independent
Requires-Python: >=3.10
License-File: LICENSE
Requires-Dist: Cython==3.0.11
Provides-Extra: dev
Requires-Dist: twine==5.1.1; extra == "dev"
Requires-Dist: pre-commit==4.0.1; extra == "dev"
Requires-Dist: pytest==8.3.3; extra == "dev"
Requires-Dist: copier==9.4.1; extra == "dev"
